{
  "generatedAt": "2026-03-25T09:08:45+00:00",
  "items": [
    {
      "id": "latest_19801bc1233a",
      "section": "latest",
      "sectionLabel": "Latest",
      "type": "REAL",
      "category": "WORLD",
      "title": "Shock as dozens of bodies, mostly infants, discovered in Kenya mass grave",
      "dek": "Some of the 32 bodies, including 25 children, are believed to have come from local hospitals and mortuaries.",
      "body": "Some of the 32 bodies, including 25 children, are believed to have come from local hospitals and mortuaries.",
      "author": "IriLine Desk",
      "publishedAt": "2026-03-25T08:41:22+00:00",
      "sourceUrl": "https://www.bbc.com/news/articles/clydj9gj24jo?at_medium=RSS&at_campaign=rss",
      "image": "https://ichef.bbci.co.uk/ace/standard/240/cpsprodpb/d113/live/771c79b0-2822-11f1-9fca-7da6a2456b50.jpg",
      "imageCredit": "Image via original publisher"
    },
    {
      "id": "latest_ee805868bb51",
      "section": "latest",
      "sectionLabel": "Latest",
      "type": "REAL",
      "category": "WORLD",
      "title": "Graffiti conviction for Australian woman who stuck googly eyes on sculpture",
      "dek": "The woman had taken MDMA and three litres of vodka when she vandalised the piece nicknamed Blue Blob.",
      "body": "The woman had taken MDMA and three litres of vodka when she vandalised the piece nicknamed Blue Blob.",
      "author": "IriLine Desk",
      "publishedAt": "2026-03-25T08:17:51+00:00",
      "sourceUrl": "https://www.bbc.com/news/articles/cwydx34kzlvo?at_medium=RSS&at_campaign=rss",
      "image": "https://ichef.bbci.co.uk/ace/standard/240/cpsprodpb/59e2/live/0c749460-281f-11f1-a79a-77e93010d956.png",
      "imageCredit": "Image via original publisher"
    },
    {
      "id": "meme_57ca3abd17a9",
      "section": "meme",
      "sectionLabel": "Not-So-Serious",
      "type": "MEME",
      "category": "WEIRD",
      "title": "Man arrested after crossbow attack on stranger in Switzerland",
      "dek": "submitted by /u/Sudden-Ad-4281 [link] [comments]",
      "body": "submitted by /u/Sudden-Ad-4281 [link] [comments]",
      "author": "IriLine Desk",
      "publishedAt": "2026-03-25T07:30:04+00:00",
      "sourceUrl": "https://www.reddit.com/r/nottheonion/comments/1s343fp/man_arrested_after_crossbow_attack_on_stranger_in/",
      "image": "https://external-preview.redd.it/zNOyR2PLo4CV7ma3ziWwx_g7f44ygmWDWJKob7tOtZM.jpeg?width=640&crop=smart&auto=webp&s=e4cece41d3c768af8afb2acd53b8427d94b7d03e",
      "imageCredit": "Image via original publisher"
    }
  ]
}