{
  "generatedAt": "2026-06-08T07:03:13+00:00",
  "items": [
    {
      "id": "latest_d467cdd8d860",
      "section": "latest",
      "sectionLabel": "Latest",
      "type": "REAL",
      "category": "WORLD",
      "title": "Rare footage captured of Great White shark in Mediterranean Sea",
      "dek": "A volunteer diver has described shaking as he filmed his encounter with an endangered Great White shark between Tunisia and Sicily.",
      "body": "A volunteer diver has described shaking as he filmed his encounter with an endangered Great White shark between Tunisia and Sicily.",
      "author": "IriLine Desk",
      "publishedAt": "2026-06-08T06:09:53+00:00",
      "sourceUrl": "https://www.bbc.com/news/videos/cd6p6zqzj6do?at_medium=RSS&at_campaign=rss",
      "image": "https://ichef.bbci.co.uk/ace/standard/240/cpsprodpb/b48b/live/a1b6a3e0-60e3-11f1-82ca-1380a42b6773.jpg",
      "imageCredit": "Image via original publisher"
    },
    {
      "id": "latest_d467cdd8d860",
      "section": "latest",
      "sectionLabel": "Latest",
      "type": "REAL",
      "category": "WORLD",
      "title": "Rare footage captured of Great White shark in Mediterranean Sea",
      "dek": "A volunteer diver has described shaking as he filmed his encounter with an endangered Great White shark between Tunisia and Sicily.",
      "body": "A volunteer diver has described shaking as he filmed his encounter with an endangered Great White shark between Tunisia and Sicily.",
      "author": "IriLine Desk",
      "publishedAt": "2026-06-08T06:09:53+00:00",
      "sourceUrl": "https://www.bbc.com/news/videos/cd6p6zqzj6do?at_medium=RSS&at_campaign=rss",
      "image": "https://ichef.bbci.co.uk/ace/standard/240/cpsprodpb/b48b/live/a1b6a3e0-60e3-11f1-82ca-1380a42b6773.jpg",
      "imageCredit": "Image via original publisher"
    },
    {
      "id": "meme_59f3521f405e",
      "section": "meme",
      "sectionLabel": "Not-So-Serious",
      "type": "MEME",
      "category": "WEIRD",
      "title": "Caught on camera: Shelbyville mayor insinuates citizens opposing data centers are poor renters in ‘sh***y houses’",
      "dek": "submitted by /u/Polyphagous_person [link] [comments]",
      "body": "submitted by /u/Polyphagous_person [link] [comments]",
      "author": "IriLine Desk",
      "publishedAt": "2026-06-08T04:21:07+00:00",
      "sourceUrl": "https://www.reddit.com/r/nottheonion/comments/1tzxj41/caught_on_camera_shelbyville_mayor_insinuates/",
      "image": "https://external-preview.redd.it/usKOOZZ4DOTKFzqZf3QopQ6jAv1ZEoS3vkCQGs3fhbk.jpeg?width=640&crop=smart&auto=webp&s=d180388f9d91a9e8a081fc59b14d7019e2966f03",
      "imageCredit": "Image via original publisher"
    }
  ]
}