{
  "generatedAt": "2026-04-17T11:36:08+00:00",
  "items": [
    {
      "id": "latest_bad34917dbdc",
      "section": "latest",
      "sectionLabel": "Latest",
      "type": "REAL",
      "category": "WORLD",
      "title": "BBC in Iran: 'Tehran does not think it has lost this war'",
      "dek": "Lyse Doucet says Iranians want a solution to the long-running animosity with the US, but leaders is not willing to make a deal on Washington's terms.",
      "body": "Lyse Doucet says Iranians want a solution to the long-running animosity with the US, but leaders is not willing to make a deal on Washington's terms.",
      "author": "IriLine Desk",
      "publishedAt": "2026-04-17T09:19:23+00:00",
      "sourceUrl": "https://www.bbc.com/news/videos/clyxp0kp5glo?at_medium=RSS&at_campaign=rss",
      "image": "https://ichef.bbci.co.uk/ace/standard/240/cpsprodpb/59b2/live/9d32f210-3a37-11f1-9d5c-8ba507d7dbde.jpg",
      "imageCredit": "Image via original publisher"
    },
    {
      "id": "latest_78c25feaeb4c",
      "section": "latest",
      "sectionLabel": "Latest",
      "type": "REAL",
      "category": "WORLD",
      "title": "Avengers reassemble and Top Gun flies back - Hollywood studios preview their new movies",
      "dek": "Some of the most hotly anticipated new films of the next couple of years are previewed at CinemaCon.",
      "body": "Some of the most hotly anticipated new films of the next couple of years are previewed at CinemaCon.",
      "author": "IriLine Desk",
      "publishedAt": "2026-04-17T08:30:34+00:00",
      "sourceUrl": "https://www.bbc.com/news/articles/cwyk2xrkvnzo?at_medium=RSS&at_campaign=rss",
      "image": "https://ichef.bbci.co.uk/ace/standard/240/cpsprodpb/8d0a/live/7cb15140-3a31-11f1-ae6d-5b9ff237458e.jpg",
      "imageCredit": "Image via original publisher"
    },
    {
      "id": "latest_182a9109f3ec",
      "section": "latest",
      "sectionLabel": "Latest",
      "type": "REAL",
      "category": "WORLD",
      "title": "Three charged with arson on Persian media offices in London",
      "dek": "Two teenagers and a 21-year-old man are due in court charged with arson with intent to endanger life.",
      "body": "Two teenagers and a 21-year-old man are due in court charged with arson with intent to endanger life.",
      "author": "IriLine Desk",
      "publishedAt": "2026-04-17T08:22:33+00:00",
      "sourceUrl": "https://www.bbc.com/news/articles/cwyv24lx1r8o?at_medium=RSS&at_campaign=rss",
      "image": "https://ichef.bbci.co.uk/ace/standard/240/cpsprodpb/af0a/live/2f04d6c0-3a35-11f1-8606-05fe34b06e1b.jpg",
      "imageCredit": "Image via original publisher"
    }
  ]
}