{
  "generatedAt": "2026-02-27T15:52:25+00:00",
  "items": [
    {
      "id": "latest_a81e550c34e4",
      "section": "latest",
      "sectionLabel": "Latest",
      "type": "REAL",
      "category": "WORLD",
      "title": "'Obnoxious' AI chatbot talked about its mother, customers say",
      "dek": "Australian supermarket giant Woolworths tweaks its AI-powered assistant after users said it gave them the \"ick\".",
      "body": "Australian supermarket giant Woolworths tweaks its AI-powered assistant after users said it gave them the \"ick\".",
      "author": "IriLine Desk",
      "publishedAt": "2026-02-27T15:47:20+00:00",
      "sourceUrl": "https://www.bbc.com/news/articles/cy7jeyeyd18o?at_medium=RSS&at_campaign=rss",
      "image": "https://ichef.bbci.co.uk/ace/standard/240/cpsprodpb/aec9/live/b4166720-13ed-11f1-82ca-eb805bf206d6.jpg",
      "imageCredit": "Image via original publisher"
    },
    {
      "id": "latest_5c79fa1cda93",
      "section": "latest",
      "sectionLabel": "Latest",
      "type": "REAL",
      "category": "WORLD",
      "title": "UK withdraws Tehran embassy staff as US-Iran tension sparks concern across region",
      "dek": "The US embassy in Israel has also told some non-emergency staff they can leave the country if they wish.",
      "body": "The US embassy in Israel has also told some non-emergency staff they can leave the country if they wish.",
      "author": "IriLine Desk",
      "publishedAt": "2026-02-27T15:13:58+00:00",
      "sourceUrl": "https://www.bbc.com/news/articles/c309vz0z893o?at_medium=RSS&at_campaign=rss",
      "image": "https://ichef.bbci.co.uk/ace/standard/240/cpsprodpb/3d14/live/612adfe0-13ee-11f1-82ca-eb805bf206d6.jpg",
      "imageCredit": "Image via original publisher"
    },
    {
      "id": "latest_2359090a95d4",
      "section": "latest",
      "sectionLabel": "Latest",
      "type": "REAL",
      "category": "WORLD",
      "title": "Pakistan defence minister says country in 'open war' with Afghanistan after strikes",
      "dek": "The latest attacks by Pakistan follow months of clashes between the two countries. despite agreeing to a fragile ceasefire in October.",
      "body": "The latest attacks by Pakistan follow months of clashes between the two countries. despite agreeing to a fragile ceasefire in October.",
      "author": "IriLine Desk",
      "publishedAt": "2026-02-27T13:19:18+00:00",
      "sourceUrl": "https://www.bbc.com/news/articles/cvgjd7pv4y4o?at_medium=RSS&at_campaign=rss",
      "image": "https://ichef.bbci.co.uk/ace/standard/240/cpsprodpb/028d/live/78630be0-13c8-11f1-8c68-835571867502.jpg",
      "imageCredit": "Image via original publisher"
    }
  ]
}