{
  "generatedAt": "2026-05-07T07:42:52+00:00",
  "items": [
    {
      "id": "latest_660a31dcfd93",
      "section": "latest",
      "sectionLabel": "Latest",
      "type": "REAL",
      "category": "WORLD",
      "title": "Shell profits rise as Iran war pushes oil prices higher",
      "dek": "The energy giant reports profits of $6.92bn for the first three months of the year.",
      "body": "The energy giant reports profits of $6.92bn for the first three months of the year.",
      "author": "IriLine Desk",
      "publishedAt": "2026-05-07T07:27:08+00:00",
      "sourceUrl": "https://www.bbc.com/news/articles/ce3p0x54drwo?at_medium=RSS&at_campaign=rss",
      "image": "https://ichef.bbci.co.uk/ace/standard/240/cpsprodpb/d823/live/94684120-49d8-11f1-9acb-332348f2c41f.jpg",
      "imageCredit": "Image via original publisher"
    },
    {
      "id": "latest_9f3fda52e0c8",
      "section": "latest",
      "sectionLabel": "Latest",
      "type": "REAL",
      "category": "WORLD",
      "title": "Ukraine is a global surrogacy hub - but that could be about to end",
      "dek": "Ukraine is considering a law that would effectively ban foreigners from accessing surrogacy in the country.",
      "body": "Ukraine is considering a law that would effectively ban foreigners from accessing surrogacy in the country.",
      "author": "IriLine Desk",
      "publishedAt": "2026-05-07T05:02:12+00:00",
      "sourceUrl": "https://www.bbc.com/news/articles/clyp4kp687go?at_medium=RSS&at_campaign=rss",
      "image": "https://ichef.bbci.co.uk/ace/standard/240/cpsprodpb/dd4d/live/992a5b50-494f-11f1-bd44-e578c5bd51ff.png",
      "imageCredit": "Image via original publisher"
    },
    {
      "id": "latest_7bc2fe1faa4a",
      "section": "latest",
      "sectionLabel": "Latest",
      "type": "REAL",
      "category": "WORLD",
      "title": "Looksmaxxing influencer Clavicular charged over alleged alligator shooting",
      "dek": "The looksmaxxing influencer allegedly livestreamed himself firing gunshots from an airboat at an alligator.",
      "body": "The looksmaxxing influencer allegedly livestreamed himself firing gunshots from an airboat at an alligator.",
      "author": "IriLine Desk",
      "publishedAt": "2026-05-07T04:50:18+00:00",
      "sourceUrl": "https://www.bbc.com/news/articles/c62ex04n876o?at_medium=RSS&at_campaign=rss",
      "image": "https://ichef.bbci.co.uk/ace/standard/240/cpsprodpb/3705/live/fd4a60c0-49be-11f1-9739-d3421ea39759.jpg",
      "imageCredit": "Image via original publisher"
    }
  ]
}