{
  "generatedAt": "2026-04-25T06:57:13+00:00",
  "items": [
    {
      "id": "sports_8c39e302e9dc",
      "section": "sports",
      "sectionLabel": "Sports",
      "type": "REAL",
      "category": "SPORTS",
      "title": "Udoka calls out Rockets after collapse: 'Grow up'",
      "dek": "Rockets coach Ime Udoka called out his team after a late-game collapse that saw Houston fall into a 3-0 series hole against the Lakers. \"Horrendous mistakes,\" h",
      "body": "Rockets coach Ime Udoka called out his team after a late-game collapse that saw Houston fall into a 3-0 series hole against the Lakers. \"Horrendous mistakes,\" he said. \"I don't know if you want to say youth or scared of the moment, or whatever the case.\"",
      "author": "IriLine Desk",
      "publishedAt": "2026-04-25T01:56:35+00:00",
      "sourceUrl": "https://www.espn.com/nba/story/_/id/48587123/ime-udoka-calls-rockets-game-3-collapse-vs-lakers-youth-scared-moment",
      "image": "https://source.unsplash.com/1600x900/?news&sig=sports_8c39e302e9dc",
      "imageCredit": "Photo via Unsplash (free to use)"
    },
    {
      "id": "latest_1e7a3939ce76",
      "section": "latest",
      "sectionLabel": "Latest",
      "type": "REAL",
      "category": "WORLD",
      "title": "Dozens of sloths died before opening of Sloth World attraction in Florida",
      "dek": "Many died due to conditions at a Florida warehouse where they'd been shipped, while others arrived from South America dead, authorities say.",
      "body": "Many died due to conditions at a Florida warehouse where they'd been shipped, while others arrived from South America dead, authorities say.",
      "author": "IriLine Desk",
      "publishedAt": "2026-04-25T01:42:58+00:00",
      "sourceUrl": "https://www.bbc.com/news/articles/cz675j3y151o?at_medium=RSS&at_campaign=rss",
      "image": "https://ichef.bbci.co.uk/ace/standard/240/cpsprodpb/4dba/live/87570de0-3e93-11f1-b83a-1531f70021ef.jpg",
      "imageCredit": "Image via original publisher"
    },
    {
      "id": "latest_0f523148c220",
      "section": "latest",
      "sectionLabel": "Latest",
      "type": "REAL",
      "category": "WORLD",
      "title": "Heated Rivalry, The Housemaid and Fourth Wing: TikTok launches BookTok bestseller list",
      "dek": "The inaugural top 20 is entirely made up of female authors, with Chloe Walsh appearing most frequently.",
      "body": "The inaugural top 20 is entirely made up of female authors, with Chloe Walsh appearing most frequently.",
      "author": "IriLine Desk",
      "publishedAt": "2026-04-25T01:38:59+00:00",
      "sourceUrl": "https://www.bbc.com/news/articles/c5yxmy5gnd0o?at_medium=RSS&at_campaign=rss",
      "image": "https://ichef.bbci.co.uk/ace/standard/240/cpsprodpb/cffe/live/33a22000-3ff0-11f1-ac78-2112837ce2aa.jpg",
      "imageCredit": "Image via original publisher"
    }
  ]
}