{
  "generatedAt": "2026-06-23T14:04:55+00:00",
  "items": [
    {
      "id": "latest_51ae51d4c53b",
      "section": "latest",
      "sectionLabel": "Latest",
      "type": "REAL",
      "category": "WORLD",
      "title": "Irish government to contribute £197m to cross-border rail services",
      "dek": "The money will come from the last allocation from the Irish government's Shared Island Fund.",
      "body": "The money will come from the last allocation from the Irish government's Shared Island Fund.",
      "author": "IriLine Desk",
      "publishedAt": "2026-06-23T13:39:03+00:00",
      "sourceUrl": "https://www.bbc.co.uk/news/articles/cd95yd1y050o?at_medium=RSS&at_campaign=rss",
      "image": "https://ichef.bbci.co.uk/ace/standard/240/cpsprodpb/13e2/live/f49071f0-6f06-11f1-87e9-1dc598ae70b3.jpg",
      "imageCredit": "Image via original publisher"
    },
    {
      "id": "meme_7aa0a5087b5f",
      "section": "meme",
      "sectionLabel": "Not-So-Serious",
      "type": "MEME",
      "category": "WEIRD",
      "title": "Larry the cat outlasts sixth UK Prime Minister as Kier Starmer resigns",
      "dek": "submitted by /u/Yeetinthebox [link] [comments]",
      "body": "submitted by /u/Yeetinthebox [link] [comments]",
      "author": "IriLine Desk",
      "publishedAt": "2026-06-23T13:01:52+00:00",
      "sourceUrl": "https://www.reddit.com/r/nottheonion/comments/1udgjfq/larry_the_cat_outlasts_sixth_uk_prime_minister_as/",
      "image": "https://source.unsplash.com/1600x900/?news&sig=meme_7aa0a5087b5f",
      "imageCredit": "Photo via Unsplash (free to use)"
    },
    {
      "id": "latest_eae473dd8c69",
      "section": "latest",
      "sectionLabel": "Latest",
      "type": "REAL",
      "category": "WORLD",
      "title": "Zambia ex-president's family wins latest legal battle over what should happen to his body",
      "dek": "Edgar Lungu's family and the Zambian government remain in dispute 12 months after he died.",
      "body": "Edgar Lungu's family and the Zambian government remain in dispute 12 months after he died.",
      "author": "IriLine Desk",
      "publishedAt": "2026-06-23T12:02:29+00:00",
      "sourceUrl": "https://www.bbc.co.uk/news/articles/c8r2yryr5mvo?at_medium=RSS&at_campaign=rss",
      "image": "https://ichef.bbci.co.uk/ace/standard/240/cpsprodpb/5334/live/cd486880-77a1-11f0-ac7b-4783efd8e136.jpg",
      "imageCredit": "Image via original publisher"
    }
  ]
}