{
  "generatedAt": "2026-03-13T15:57:48+00:00",
  "items": [
    {
      "id": "meme_ad1a8efc1506",
      "section": "meme",
      "sectionLabel": "Not-So-Serious",
      "type": "MEME",
      "category": "WEIRD",
      "title": "Pete Hegseth on Strait of Hormuz: 'Don't need to worry about it'",
      "dek": "submitted by /u/view9234 [link] [comments]",
      "body": "submitted by /u/view9234 [link] [comments]",
      "author": "IriLine Desk",
      "publishedAt": "2026-03-13T15:38:46+00:00",
      "sourceUrl": "https://www.reddit.com/r/nottheonion/comments/1rsqpcx/pete_hegseth_on_strait_of_hormuz_dont_need_to/",
      "image": "https://external-preview.redd.it/PcJVCk5chneC_prt4MjpJqDZtscxkvePDCVLKcJAhp8.jpeg?width=640&crop=smart&auto=webp&s=6ff2825bb227ecf57dc709a731a6a6dccaae860c",
      "imageCredit": "Image via original publisher"
    },
    {
      "id": "meme_f0b2150d3575",
      "section": "meme",
      "sectionLabel": "Not-So-Serious",
      "type": "MEME",
      "category": "WEIRD",
      "title": "Morrissey 'too tired' to perform, and 12 other excuses for cancelled concerts",
      "dek": "submitted by /u/xrayvision1 [link] [comments]",
      "body": "submitted by /u/xrayvision1 [link] [comments]",
      "author": "IriLine Desk",
      "publishedAt": "2026-03-13T14:40:08+00:00",
      "sourceUrl": "https://www.reddit.com/r/nottheonion/comments/1rsp4yo/morrissey_too_tired_to_perform_and_12_other/",
      "image": "https://external-preview.redd.it/_QLaL_FeEAyKIPq5q3EWCTyu6TN1ohxwEziAYeVDvS0.jpeg?width=640&crop=smart&auto=webp&s=40b84407a4630fb25c2bccf3b04e357ccf1ee901",
      "imageCredit": "Image via original publisher"
    },
    {
      "id": "latest_9cdfd4294fe9",
      "section": "latest",
      "sectionLabel": "Latest",
      "type": "REAL",
      "category": "WORLD",
      "title": "Cuba says it will release 51 prisoners in the coming days",
      "dek": "Havana says it is in talks with Washington as no fuel has entered the island in three months.",
      "body": "Havana says it is in talks with Washington as no fuel has entered the island in three months.",
      "author": "IriLine Desk",
      "publishedAt": "2026-03-13T14:17:06+00:00",
      "sourceUrl": "https://www.bbc.com/news/articles/cwy8zv9gp0go?at_medium=RSS&at_campaign=rss",
      "image": "https://ichef.bbci.co.uk/ace/standard/240/cpsprodpb/7776/live/38b9d650-1ed0-11f1-b8f6-b15aa2adfcf4.jpg",
      "imageCredit": "Image via original publisher"
    }
  ]
}