{
  "generatedAt": "2026-02-14T13:45:23+00:00",
  "items": [
    {
      "id": "latest_f30060e22617",
      "section": "latest",
      "sectionLabel": "Latest",
      "type": "REAL",
      "category": "WORLD",
      "title": "Casey Wasserman to sell talent agency after Epstein fallout - reports",
      "dek": "The prominent agent and LA Olympics chief has come under scrutiny over past ties with Jeffrey Epstein and Ghislaine Maxwell.",
      "body": "The prominent agent and LA Olympics chief has come under scrutiny over past ties with Jeffrey Epstein and Ghislaine Maxwell.",
      "author": "IriLine Desk",
      "publishedAt": "2026-02-14T13:28:26+00:00",
      "sourceUrl": "https://www.bbc.com/news/articles/cy0dn4e1njjo?at_medium=RSS&at_campaign=rss",
      "image": "https://ichef.bbci.co.uk/ace/standard/240/cpsprodpb/de77/live/7b579890-09a8-11f1-acb3-91fbf84be714.jpg",
      "imageCredit": "Image via original publisher"
    },
    {
      "id": "meme_6dc83391b1fa",
      "section": "meme",
      "sectionLabel": "Not-So-Serious",
      "type": "MEME",
      "category": "WEIRD",
      "title": "NATO’s Secretary General Said a Ukrainian Dog “Promised Not to Surrender.”",
      "dek": "submitted by /u/sergeyfomkin [link] [comments]",
      "body": "submitted by /u/sergeyfomkin [link] [comments]",
      "author": "IriLine Desk",
      "publishedAt": "2026-02-14T13:14:58+00:00",
      "sourceUrl": "https://www.reddit.com/r/nottheonion/comments/1r4kch1/natos_secretary_general_said_a_ukrainian_dog/",
      "image": "https://external-preview.redd.it/8TcNJFvAKG31eEE_2GlzKz_aDI_tBQkSWPbM0WqUYu0.jpeg?width=640&crop=smart&auto=webp&s=332fcc014576ffe7ee524b4ce219df007679739c",
      "imageCredit": "Image via original publisher"
    },
    {
      "id": "meme_d4879b735b61",
      "section": "meme",
      "sectionLabel": "Not-So-Serious",
      "type": "MEME",
      "category": "WEIRD",
      "title": "Iran Elected Vice Chair of UN Social Development Commission",
      "dek": "submitted by /u/ExtremeMacarons [link] [comments]",
      "body": "submitted by /u/ExtremeMacarons [link] [comments]",
      "author": "IriLine Desk",
      "publishedAt": "2026-02-14T13:08:26+00:00",
      "sourceUrl": "https://www.reddit.com/r/nottheonion/comments/1r4k7m1/iran_elected_vice_chair_of_un_social_development/",
      "image": "https://external-preview.redd.it/MLPVFTCNSe_jONVeiCt2FTK1ZiJ4efSwVlttgR91b_M.jpeg?width=640&crop=smart&auto=webp&s=0ee879716804040c56bb38dfac7f869bb0c6b72c",
      "imageCredit": "Image via original publisher"
    }
  ]
}