{
  "generatedAt": "2026-02-08T02:37:27+00:00",
  "items": [
    {
      "id": "meme_bda1f0ee51ec",
      "section": "meme",
      "sectionLabel": "Not-So-Serious",
      "type": "MEME",
      "category": "WEIRD",
      "title": "Homeland Security Spying on Reddit Users",
      "dek": "submitted by /u/StemCellPirate [link] [comments]",
      "body": "submitted by /u/StemCellPirate [link] [comments]",
      "author": "IriLine Desk",
      "publishedAt": "2026-02-08T02:03:05+00:00",
      "sourceUrl": "https://www.reddit.com/r/nottheonion/comments/1qywbje/homeland_security_spying_on_reddit_users/",
      "image": "https://external-preview.redd.it/cbskIU9Ks0Ox27wwym6AdcdRAGNrR0QBDVHalkK-vLo.jpeg?width=640&crop=smart&auto=webp&s=1c622105a7d0c9caf10852b4adabbf861b8686b7",
      "imageCredit": "Image via original publisher"
    },
    {
      "id": "latest_855d06269ac6",
      "section": "latest",
      "sectionLabel": "Latest",
      "type": "REAL",
      "category": "WORLD",
      "title": "Savannah Guthrie says 'we will pay' for mother's safe return",
      "dek": "\"We received your message,\" the US news anchor says in the latest video plea for the return of her mother Nancy Guthrie, 84, who is believed abducted.",
      "body": "\"We received your message,\" the US news anchor says in the latest video plea for the return of her mother Nancy Guthrie, 84, who is believed abducted.",
      "author": "IriLine Desk",
      "publishedAt": "2026-02-08T01:58:07+00:00",
      "sourceUrl": "https://www.bbc.com/news/articles/ce9y99eg0nno?at_medium=RSS&at_campaign=rss",
      "image": "https://ichef.bbci.co.uk/ace/standard/240/cpsprodpb/4726/live/c0223680-0492-11f1-b5e2-dd58fc65f0f6.jpg",
      "imageCredit": "Image via original publisher"
    },
    {
      "id": "meme_38b77915b4cd",
      "section": "meme",
      "sectionLabel": "Not-So-Serious",
      "type": "MEME",
      "category": "WEIRD",
      "title": "Lawsuit against Tesla reveals harrowing 911 call as driver trapped in burning car",
      "dek": "submitted by /u/Illustrious_Tax_9769 [link] [comments]",
      "body": "submitted by /u/Illustrious_Tax_9769 [link] [comments]",
      "author": "IriLine Desk",
      "publishedAt": "2026-02-08T01:30:27+00:00",
      "sourceUrl": "https://www.reddit.com/r/nottheonion/comments/1qyvm0n/lawsuit_against_tesla_reveals_harrowing_911_call/",
      "image": "https://external-preview.redd.it/2PScc-d-x7Ro6HDE6z09kG7EnYljGUGEL9J9Z2WOXL0.jpeg?width=640&crop=smart&auto=webp&s=a5b7a9713b260a1a2d4d17d4d0951c40a3668d78",
      "imageCredit": "Image via original publisher"
    },
    {
      "id": "meme_25dcf40516c9",
      "section": "meme",
      "sectionLabel": "Not-So-Serious",
      "type": "MEME",
      "category": "WEIRD",
      "title": "Reddit mod deleted NASA astronaut’s space photo for being “blurry”",
      "dek": "submitted by /u/Superb_Trainer_2967 [link] [comments]",
      "body": "submitted by /u/Superb_Trainer_2967 [link] [comments]",
      "author": "IriLine Desk",
      "publishedAt": "2026-02-08T01:04:06+00:00",
      "sourceUrl": "https://www.reddit.com/r/nottheonion/comments/1qyv1hr/reddit_mod_deleted_nasa_astronauts_space_photo/",
      "image": "https://external-preview.redd.it/nvrxwmPuBVP2hOdqRtA9eiQc3IwbUuRzjVBciUfTx0k.jpeg?width=640&crop=smart&auto=webp&s=e615e5292b8a94e424ffc2919f1a04311b957f51",
      "imageCredit": "Image via original publisher"
    },
    {
      "id": "latest_0911862bb78f",
      "section": "latest",
      "sectionLabel": "Latest",
      "type": "REAL",
      "category": "WORLD",
      "title": "From classroom to camera: A teacher who has become a sensation in Indian cinema",
      "dek": "At 70, indigenous teacher Biana Watre Momin acted in an Indian film that has changed her life.",
      "body": "At 70, indigenous teacher Biana Watre Momin acted in an Indian film that has changed her life.",
      "author": "IriLine Desk",
      "publishedAt": "2026-02-08T00:57:50+00:00",
      "sourceUrl": "https://www.bbc.com/news/articles/c20zzn77w82o?at_medium=RSS&at_campaign=rss",
      "image": "https://ichef.bbci.co.uk/ace/standard/240/cpsprodpb/643d/live/bf8d2340-f82d-11f0-a422-4ba8a094a8fa.jpg",
      "imageCredit": "Image via original publisher"
    },
    {
      "id": "meme_639b1c6f0669",
      "section": "meme",
      "sectionLabel": "Not-So-Serious",
      "type": "MEME",
      "category": "WEIRD",
      "title": "RFK Jr.’s Dinosaur Hunt With Jeffrey Epstein: How Science Trips Became Epstein’s Unlikely Path to Influence",
      "dek": "submitted by /u/StemCellPirate [link] [comments]",
      "body": "submitted by /u/StemCellPirate [link] [comments]",
      "author": "IriLine Desk",
      "publishedAt": "2026-02-08T00:52:05+00:00",
      "sourceUrl": "https://www.reddit.com/r/nottheonion/comments/1qyuryi/rfk_jrs_dinosaur_hunt_with_jeffrey_epstein_how/",
      "image": "https://external-preview.redd.it/6sTwgWKhPjNz3Q2-KrTFQqpYnOsbcFLygjDHi-OM6JI.jpeg?width=640&crop=smart&auto=webp&s=8decc43ae4132a2eec7757be1e707ffee30e3942",
      "imageCredit": "Image via original publisher"
    },
    {
      "id": "latest_3b9988b083db",
      "section": "latest",
      "sectionLabel": "Latest",
      "type": "REAL",
      "category": "WORLD",
      "title": "Washington Post chief executive steps down after mass lay-offs",
      "dek": "Will Lewis said \"difficult decisions\" had been made to ensure the newspaper's future.",
      "body": "Will Lewis said \"difficult decisions\" had been made to ensure the newspaper's future.",
      "author": "IriLine Desk",
      "publishedAt": "2026-02-08T00:51:45+00:00",
      "sourceUrl": "https://www.bbc.com/news/articles/c8e5ee39j47o?at_medium=RSS&at_campaign=rss",
      "image": "https://ichef.bbci.co.uk/ace/standard/240/cpsprodpb/9dfe/live/c6089a10-0485-11f1-b7e1-afb6d0884c18.jpg",
      "imageCredit": "Image via original publisher"
    },
    {
      "id": "meme_9e51d4fa1a0f",
      "section": "meme",
      "sectionLabel": "Not-So-Serious",
      "type": "MEME",
      "category": "WEIRD",
      "title": "Man breaks into Little Caesars twice and sells pizzas after hours, police say",
      "dek": "submitted by /u/Superb_Trainer_2967 [link] [comments]",
      "body": "submitted by /u/Superb_Trainer_2967 [link] [comments]",
      "author": "IriLine Desk",
      "publishedAt": "2026-02-08T00:07:01+00:00",
      "sourceUrl": "https://www.reddit.com/r/nottheonion/comments/1qytrb7/man_breaks_into_little_caesars_twice_and_sells/",
      "image": "https://external-preview.redd.it/SusBHp6T09v5CrqEdnYs_LbunlaJPqEqArUYq-XIxOc.jpeg?width=640&crop=smart&auto=webp&s=f37c2388e3b5a165e7ffb68538123d995d8e0ed0",
      "imageCredit": "Image via original publisher"
    },
    {
      "id": "latest_f7e4ba454538",
      "section": "latest",
      "sectionLabel": "Latest",
      "type": "REAL",
      "category": "WORLD",
      "title": "Famous but deadly kite flying festival returns after 19-year ban",
      "dek": "After injuries and fatalities caused by sharp strings, falls and celebratory gunfire, an event that dates back centuries returns.",
      "body": "After injuries and fatalities caused by sharp strings, falls and celebratory gunfire, an event that dates back centuries returns.",
      "author": "IriLine Desk",
      "publishedAt": "2026-02-08T00:01:49+00:00",
      "sourceUrl": "https://www.bbc.com/news/articles/c1dkd5ql91lo?at_medium=RSS&at_campaign=rss",
      "image": "https://ichef.bbci.co.uk/ace/standard/240/cpsprodpb/b3ff/live/407315f0-0468-11f1-b7e1-afb6d0884c18.jpg",
      "imageCredit": "Image via original publisher"
    },
    {
      "id": "latest_a0f8cd9ba715",
      "section": "latest",
      "sectionLabel": "Latest",
      "type": "REAL",
      "category": "WORLD",
      "title": "A singer's tragic death highlights Nigeria's snakebite problem",
      "dek": "The crisis is compounded by a critical shortage of affordable, properly stored antivenom.",
      "body": "The crisis is compounded by a critical shortage of affordable, properly stored antivenom.",
      "author": "IriLine Desk",
      "publishedAt": "2026-02-08T00:01:32+00:00",
      "sourceUrl": "https://www.bbc.com/news/articles/cdjn1zwm0g7o?at_medium=RSS&at_campaign=rss",
      "image": "https://ichef.bbci.co.uk/ace/standard/240/cpsprodpb/ae1d/live/427c4b50-03d7-11f1-b5e2-dd58fc65f0f6.jpg",
      "imageCredit": "Image via original publisher"
    },
    {
      "id": "latest_fbc9895b095c",
      "section": "latest",
      "sectionLabel": "Latest",
      "type": "REAL",
      "category": "WORLD",
      "title": "ICE protester speaks out after White House shared fake arrest image",
      "dek": "The White House posted an edited image of Nekima Levy Armstrong after she was arrested for organising a protest in a church.",
      "body": "The White House posted an edited image of Nekima Levy Armstrong after she was arrested for organising a protest in a church.",
      "author": "IriLine Desk",
      "publishedAt": "2026-02-07T23:59:43+00:00",
      "sourceUrl": "https://www.bbc.com/news/videos/c86v6p1djvqo?at_medium=RSS&at_campaign=rss",
      "image": "https://ichef.bbci.co.uk/ace/standard/240/cpsprodpb/915a/live/5fb940b0-0396-11f1-9972-d3f265c101c6.png",
      "imageCredit": "Image via original publisher"
    },
    {
      "id": "meme_bef5c0b2d091",
      "section": "meme",
      "sectionLabel": "Not-So-Serious",
      "type": "MEME",
      "category": "WEIRD",
      "title": "Bar raises entry age after surge in fake IDs, including one with Ben Franklin’s picture",
      "dek": "submitted by /u/EthanOMcBride [link] [comments]",
      "body": "submitted by /u/EthanOMcBride [link] [comments]",
      "author": "IriLine Desk",
      "publishedAt": "2026-02-07T23:56:12+00:00",
      "sourceUrl": "https://www.reddit.com/r/nottheonion/comments/1qytify/bar_raises_entry_age_after_surge_in_fake_ids/",
      "image": "https://external-preview.redd.it/5c_wzdXixhyFtrJclx-XypHh4pfwKaSxXDFjJiJ5WX0.png?width=640&crop=smart&auto=webp&s=99d4994a038ad9e13929fabb81a8922f43bc30b4",
      "imageCredit": "Image via original publisher"
    },
    {
      "id": "meme_401dac920e7e",
      "section": "meme",
      "sectionLabel": "Not-So-Serious",
      "type": "MEME",
      "category": "WEIRD",
      "title": "'Do you love me?': The Viking messages unearthed on Sweden's rune stones",
      "dek": "submitted by /u/StemCellPirate [link] [comments]",
      "body": "submitted by /u/StemCellPirate [link] [comments]",
      "author": "IriLine Desk",
      "publishedAt": "2026-02-07T23:27:46+00:00",
      "sourceUrl": "https://www.reddit.com/r/nottheonion/comments/1qysuz9/do_you_love_me_the_viking_messages_unearthed_on/",
      "image": "https://external-preview.redd.it/DtSed3gGAfQ69Z3DZktrljU4t7msNkAxLdzQTDQJMgM.jpeg?width=320&crop=smart&auto=webp&s=bbf498c3afc8f792dd78cc6600b421f7c6e3128f",
      "imageCredit": "Image via original publisher"
    },
    {
      "id": "meme_f3de01ea749f",
      "section": "meme",
      "sectionLabel": "Not-So-Serious",
      "type": "MEME",
      "category": "WEIRD",
      "title": "Billionaires march leader ID'd, says effort sincere",
      "dek": "submitted by /u/case-o-nuts [link] [comments]",
      "body": "submitted by /u/case-o-nuts [link] [comments]",
      "author": "IriLine Desk",
      "publishedAt": "2026-02-07T23:18:37+00:00",
      "sourceUrl": "https://www.reddit.com/r/nottheonion/comments/1qysnck/billionaires_march_leader_idd_says_effort_sincere/",
      "image": "https://external-preview.redd.it/KDOrYADnFrr5PhYEAO-0VYhFuzOa9PTFGNN_Qsheo7g.jpeg?width=640&crop=smart&auto=webp&s=92ac72ddca4b52d8e0348375aa184a948de8515f",
      "imageCredit": "Image via original publisher"
    },
    {
      "id": "latest_8f8117072d81",
      "section": "latest",
      "sectionLabel": "Latest",
      "type": "REAL",
      "category": "WORLD",
      "title": "Japan votes in snap election as PM Takaichi takes a gamble",
      "dek": "Observers say Sanae Takaichi's personal popularity may boost the ruling party's showing at the polls.",
      "body": "Observers say Sanae Takaichi's personal popularity may boost the ruling party's showing at the polls.",
      "author": "IriLine Desk",
      "publishedAt": "2026-02-07T23:00:43+00:00",
      "sourceUrl": "https://www.bbc.com/news/articles/cx2y7d2z29xo?at_medium=RSS&at_campaign=rss",
      "image": "https://ichef.bbci.co.uk/ace/standard/240/cpsprodpb/1a77/live/e18fe320-0326-11f1-9deb-9fec290cc1e6.jpg",
      "imageCredit": "Image via original publisher"
    },
    {
      "id": "meme_96d35b917de1",
      "section": "meme",
      "sectionLabel": "Not-So-Serious",
      "type": "MEME",
      "category": "WEIRD",
      "title": "South Korean governor draws criticism for suggesting importing women for marriage as population fix",
      "dek": "submitted by /u/wewhomustnotbenamed [link] [comments]",
      "body": "submitted by /u/wewhomustnotbenamed [link] [comments]",
      "author": "IriLine Desk",
      "publishedAt": "2026-02-07T23:00:34+00:00",
      "sourceUrl": "https://www.reddit.com/r/nottheonion/comments/1qys8a4/south_korean_governor_draws_criticism_for/",
      "image": "https://external-preview.redd.it/Lvd6-NqAk-foQKY_Q6PpRYsRRDjURDdhMc-3Tgu6_iQ.jpeg?width=640&crop=smart&auto=webp&s=b9caf7735983b8ec553114e8796b6559501aa72e",
      "imageCredit": "Image via original publisher"
    },
    {
      "id": "meme_780dc1146c0d",
      "section": "meme",
      "sectionLabel": "Not-So-Serious",
      "type": "MEME",
      "category": "WEIRD",
      "title": "March for Life rally among infection sites for confirmed measles cases in DC",
      "dek": "submitted by /u/its_a_bear_dance [link] [comments]",
      "body": "submitted by /u/its_a_bear_dance [link] [comments]",
      "author": "IriLine Desk",
      "publishedAt": "2026-02-07T22:37:23+00:00",
      "sourceUrl": "https://www.reddit.com/r/nottheonion/comments/1qyrofz/march_for_life_rally_among_infection_sites_for/",
      "image": "https://external-preview.redd.it/US7uHmO9_A44gCfejCrQP4QfJB8NcWUqqQa10Jn6k0U.jpeg?width=640&crop=smart&auto=webp&s=1ac1c74bee61fa160ece1f04669dc816345727e2",
      "imageCredit": "Image via original publisher"
    },
    {
      "id": "meme_7b23080d4aac",
      "section": "meme",
      "sectionLabel": "Not-So-Serious",
      "type": "MEME",
      "category": "WEIRD",
      "title": "When will it stop raining in the UK?",
      "dek": "submitted by /u/LiveRent3121 [link] [comments]",
      "body": "submitted by /u/LiveRent3121 [link] [comments]",
      "author": "IriLine Desk",
      "publishedAt": "2026-02-07T21:36:07+00:00",
      "sourceUrl": "https://www.reddit.com/r/nottheonion/comments/1qyq6j5/when_will_it_stop_raining_in_the_uk/",
      "image": "https://external-preview.redd.it/eKmwMzK5IDSnOcesYyMxk3TA5Jc3Y9Ic_Iqhk8HhuZY.jpeg?width=640&crop=smart&auto=webp&s=7696031d3cccede78274e6d359a720756f52d1e1",
      "imageCredit": "Image via original publisher"
    },
    {
      "id": "sports_864f277d42d2",
      "section": "sports",
      "sectionLabel": "Sports",
      "type": "REAL",
      "category": "SPORTS",
      "title": "Down 13, UNC storms back to jolt Duke on late 3",
      "dek": "Seth Trimble made a corner 3-pointer with 0.4 seconds left to lift No. 14 North Carolina past No. 4 Duke 71-68 in a stunning finish Saturday night.",
      "body": "Seth Trimble made a corner 3-pointer with 0.4 seconds left to lift No. 14 North Carolina past No. 4 Duke 71-68 in a stunning finish Saturday night.",
      "author": "IriLine Desk",
      "publishedAt": "2026-02-07T21:31:11+00:00",
      "sourceUrl": "https://www.espn.com/mens-college-basketball/story/_/id/47862991/seth-trimble-late-3-lifts-unc-no-4-duke-stunning-rivalry-finish",
      "image": "https://source.unsplash.com/1600x900/?news&sig=sports_864f277d42d2",
      "imageCredit": "Photo via Unsplash (free to use)"
    },
    {
      "id": "sports_98a57661082c",
      "section": "sports",
      "sectionLabel": "Sports",
      "type": "REAL",
      "category": "SPORTS",
      "title": "Sources: Dallas to put franchise tag on Pickens",
      "dek": "The Cowboys are expected to place their franchise tag on Pro Bowl wide receiver George Pickens, sources told ESPN.",
      "body": "The Cowboys are expected to place their franchise tag on Pro Bowl wide receiver George Pickens, sources told ESPN.",
      "author": "IriLine Desk",
      "publishedAt": "2026-02-07T21:31:11+00:00",
      "sourceUrl": "https://www.espn.com/nfl/story/_/id/47860197/cowboys-expected-put-franchise-tag-george-pickens-sources-say",
      "image": "https://source.unsplash.com/1600x900/?news&sig=sports_98a57661082c",
      "imageCredit": "Photo via Unsplash (free to use)"
    },
    {
      "id": "sports_0d6a66330538",
      "section": "sports",
      "sectionLabel": "Sports",
      "type": "REAL",
      "category": "SPORTS",
      "title": "Sengun sorry for sexist remark at female official",
      "dek": "Rockets center Alperen Sengun expressed remorse for calling a female referee a 'b----' earlier this week and said he apologized to her after the game.",
      "body": "Rockets center Alperen Sengun expressed remorse for calling a female referee a 'b----' earlier this week and said he apologized to her after the game.",
      "author": "IriLine Desk",
      "publishedAt": "2026-02-07T21:31:11+00:00",
      "sourceUrl": "https://www.espn.com/nba/story/_/id/47862390/alperen-sengun-sorry-sexist-remark-female-official",
      "image": "https://source.unsplash.com/1600x900/?news&sig=sports_0d6a66330538",
      "imageCredit": "Photo via Unsplash (free to use)"
    },
    {
      "id": "sports_e9e555ae8152",
      "section": "sports",
      "sectionLabel": "Sports",
      "type": "REAL",
      "category": "SPORTS",
      "title": "Izzo starts 'remorseful' Fears after mulling decision",
      "dek": "Michigan State coach Tom Izzo started guard Jeremy Fears against Illinois on Saturday after his sportsmanship was called into question in two straight games.",
      "body": "Michigan State coach Tom Izzo started guard Jeremy Fears against Illinois on Saturday after his sportsmanship was called into question in two straight games.",
      "author": "IriLine Desk",
      "publishedAt": "2026-02-07T21:31:11+00:00",
      "sourceUrl": "https://www.espn.com/mens-college-basketball/story/_/id/47862716/spartans-izzo-starts-remorseful-fears-mulling-decision",
      "image": "https://source.unsplash.com/1600x900/?news&sig=sports_e9e555ae8152",
      "imageCredit": "Photo via Unsplash (free to use)"
    },
    {
      "id": "sports_023a011cc382",
      "section": "sports",
      "sectionLabel": "Sports",
      "type": "REAL",
      "category": "SPORTS",
      "title": "Dunleavy denies putting Draymond in trade talks",
      "dek": "Warriors GM Mike Dunleavy denied including Draymond Green in trade conversations despite the team's pursuit of Giannis Antetokounmpo.",
      "body": "Warriors GM Mike Dunleavy denied including Draymond Green in trade conversations despite the team's pursuit of Giannis Antetokounmpo.",
      "author": "IriLine Desk",
      "publishedAt": "2026-02-07T21:31:11+00:00",
      "sourceUrl": "https://www.espn.com/nba/story/_/id/47863101/mike-dunleavy-denies-putting-draymond-green-trade-talks",
      "image": "https://source.unsplash.com/1600x900/?news&sig=sports_023a011cc382",
      "imageCredit": "Photo via Unsplash (free to use)"
    },
    {
      "id": "sports_ceb554cece36",
      "section": "sports",
      "sectionLabel": "Sports",
      "type": "REAL",
      "category": "SPORTS",
      "title": "Sources: WNBA updates housing in latest proposal",
      "dek": "The WNBA's latest CBA proposal includes for the first time some concessions on housing but does not have significant updates to revenue sharing, sources told ES",
      "body": "The WNBA's latest CBA proposal includes for the first time some concessions on housing but does not have significant updates to revenue sharing, sources told ESPN on Saturday.",
      "author": "IriLine Desk",
      "publishedAt": "2026-02-07T21:31:11+00:00",
      "sourceUrl": "https://www.espn.com/wnba/story/_/id/47862248/wnba-new-cba-proposal-includes-housing-provisions",
      "image": "https://source.unsplash.com/1600x900/?news&sig=sports_ceb554cece36",
      "imageCredit": "Photo via Unsplash (free to use)"
    },
    {
      "id": "sports_09f7de8e7bb1",
      "section": "sports",
      "sectionLabel": "Sports",
      "type": "REAL",
      "category": "SPORTS",
      "title": "Foxborough demands clarity on $8M WC funding",
      "dek": "Town officials in Foxborough, Massachusetts, are seeking clarity on the source of around $8 million they say is needed to fund public safety for this summer's W",
      "body": "Town officials in Foxborough, Massachusetts, are seeking clarity on the source of around $8 million they say is needed to fund public safety for this summer's World Cup games at Gillette Stadium, the home of the New England Patriots.",
      "author": "IriLine Desk",
      "publishedAt": "2026-02-07T21:31:11+00:00",
      "sourceUrl": "https://www.espn.com/soccer/story/_/id/47861632/world-cup-2026-foxborough-funding-security-gillette-stadium",
      "image": "https://source.unsplash.com/1600x900/?news&sig=sports_09f7de8e7bb1",
      "imageCredit": "Photo via Unsplash (free to use)"
    },
    {
      "id": "meme_773ee99ebefb",
      "section": "meme",
      "sectionLabel": "Not-So-Serious",
      "type": "MEME",
      "category": "WEIRD",
      "title": "South Korean crypto firm accidentally sends $44 billion in bitcoin to users",
      "dek": "submitted by /u/Cute-Beyond-8133 [link] [comments]",
      "body": "submitted by /u/Cute-Beyond-8133 [link] [comments]",
      "author": "IriLine Desk",
      "publishedAt": "2026-02-07T21:23:56+00:00",
      "sourceUrl": "https://www.reddit.com/r/nottheonion/comments/1qypvfk/south_korean_crypto_firm_accidentally_sends_44/",
      "image": "https://external-preview.redd.it/dy1gL6ib56A2E-e7DgJ7Z-MtLg4VbobHpuge_yn7_3Y.jpeg?width=640&crop=smart&auto=webp&s=f44c212d938397c9b2e69cf064b343c32e197351",
      "imageCredit": "Image via original publisher"
    },
    {
      "id": "latest_3d1a0cf433fc",
      "section": "latest",
      "sectionLabel": "Latest",
      "type": "REAL",
      "category": "WORLD",
      "title": "BBC debunks claims that Bad Bunny is not a US citizen",
      "dek": "On Sunday 8 February, Bad Bunny will perform at the Super Bowl half-time show to an audience of more than 100 million people across the world.",
      "body": "On Sunday 8 February, Bad Bunny will perform at the Super Bowl half-time show to an audience of more than 100 million people across the world.",
      "author": "IriLine Desk",
      "publishedAt": "2026-02-07T21:11:23+00:00",
      "sourceUrl": "https://www.bbc.com/news/videos/ckgngd10lk7o?at_medium=RSS&at_campaign=rss",
      "image": "https://ichef.bbci.co.uk/ace/standard/240/cpsprodpb/52ae/live/f1424230-0467-11f1-b5e2-dd58fc65f0f6.jpg",
      "imageCredit": "Image via original publisher"
    },
    {
      "id": "meme_697322f94342",
      "section": "meme",
      "sectionLabel": "Not-So-Serious",
      "type": "MEME",
      "category": "WEIRD",
      "title": "Inside Epstein’s House: When “Art” Becomes a Map of Power and Abuse",
      "dek": "submitted by /u/ResPublicaMgz [link] [comments]",
      "body": "submitted by /u/ResPublicaMgz [link] [comments]",
      "author": "IriLine Desk",
      "publishedAt": "2026-02-07T21:10:12+00:00",
      "sourceUrl": "https://www.reddit.com/r/nottheonion/comments/1qypizu/inside_epsteins_house_when_art_becomes_a_map_of/",
      "image": "https://external-preview.redd.it/z_NrWJg5i3SZJ-vysr50lTu54qrfh3fMl527sB3EPCw.jpeg?width=640&crop=smart&auto=webp&s=3b57d289630a083ec9023edaabcf5f653d41e01d",
      "imageCredit": "Image via original publisher"
    },
    {
      "id": "meme_25b81eab86f3",
      "section": "meme",
      "sectionLabel": "Not-So-Serious",
      "type": "MEME",
      "category": "WEIRD",
      "title": "Pentagon ends academic ties with \"woke\" Harvard",
      "dek": "submitted by /u/Disorderly_Fashion [link] [comments]",
      "body": "submitted by /u/Disorderly_Fashion [link] [comments]",
      "author": "IriLine Desk",
      "publishedAt": "2026-02-07T20:32:31+00:00",
      "sourceUrl": "https://www.reddit.com/r/nottheonion/comments/1qyokkc/pentagon_ends_academic_ties_with_woke_harvard/",
      "image": "https://external-preview.redd.it/Le9i-nVbaLbXXTsOSg-D8yNzyXnjRex4VZuOcpfMjWA.jpeg?width=640&crop=smart&auto=webp&s=36c4976a701c2ee42bafdb46c81542265374548a",
      "imageCredit": "Image via original publisher"
    },
    {
      "id": "meme_c229c49309f4",
      "section": "meme",
      "sectionLabel": "Not-So-Serious",
      "type": "MEME",
      "category": "WEIRD",
      "title": "OC coffee shop secretly operating as strip club",
      "dek": "submitted by /u/TheFrederalGovt [link] [comments]",
      "body": "submitted by /u/TheFrederalGovt [link] [comments]",
      "author": "IriLine Desk",
      "publishedAt": "2026-02-07T20:15:32+00:00",
      "sourceUrl": "https://www.reddit.com/r/nottheonion/comments/1qyo4xz/oc_coffee_shop_secretly_operating_as_strip_club/",
      "image": "https://external-preview.redd.it/Lf01fFT1FDLESSdoCCS6tA5haAnVKtQVzLYVKarbOu8.jpeg?width=640&crop=smart&auto=webp&s=ff3143b98b3361b409bfeea0a90262af3f57b700",
      "imageCredit": "Image via original publisher"
    },
    {
      "id": "meme_1b5ef7cc0597",
      "section": "meme",
      "sectionLabel": "Not-So-Serious",
      "type": "MEME",
      "category": "WEIRD",
      "title": "Police arrest ‘serial defecator' in Wisconsin after drone allegedly catches her in the act",
      "dek": "submitted by /u/captainp42 [link] [comments]",
      "body": "submitted by /u/captainp42 [link] [comments]",
      "author": "IriLine Desk",
      "publishedAt": "2026-02-07T19:45:34+00:00",
      "sourceUrl": "https://www.reddit.com/r/nottheonion/comments/1qyndpq/police_arrest_serial_defecator_in_wisconsin_after/",
      "image": "https://external-preview.redd.it/Dwue7bCULdsrdPmcPBUX8PQxEDAMIQBHSC633yPw1v4.png?width=640&crop=smart&auto=webp&s=5cbc04e7055923668a50d4a7a599fcbe4fee21ab",
      "imageCredit": "Image via original publisher"
    },
    {
      "id": "latest_b7be508504e2",
      "section": "latest",
      "sectionLabel": "Latest",
      "type": "REAL",
      "category": "WORLD",
      "title": "The woman tasked with kicking Australian kids off social media",
      "dek": "After decades working in the private tech industry, Julia Inman Grant now finds herself on the other side.",
      "body": "After decades working in the private tech industry, Julia Inman Grant now finds herself on the other side.",
      "author": "IriLine Desk",
      "publishedAt": "2026-02-07T19:22:08+00:00",
      "sourceUrl": "https://www.bbc.com/news/articles/ckgyvlgvk43o?at_medium=RSS&at_campaign=rss",
      "image": "https://ichef.bbci.co.uk/ace/standard/240/cpsprodpb/9ebb/live/dd0e8440-0327-11f1-9deb-9fec290cc1e6.jpg",
      "imageCredit": "Image via original publisher"
    },
    {
      "id": "meme_5871cdb3ab3c",
      "section": "meme",
      "sectionLabel": "Not-So-Serious",
      "type": "MEME",
      "category": "WEIRD",
      "title": "Is it Brady Tkachuk or Tkachuck? Senators captain has name misspelled in new QuickBooks ad",
      "dek": "submitted by /u/AlwaysBlaze_ [link] [comments]",
      "body": "submitted by /u/AlwaysBlaze_ [link] [comments]",
      "author": "IriLine Desk",
      "publishedAt": "2026-02-07T19:17:06+00:00",
      "sourceUrl": "https://www.reddit.com/r/nottheonion/comments/1qymnp5/is_it_brady_tkachuk_or_tkachuck_senators_captain/",
      "image": "https://external-preview.redd.it/Q07TtpigqhefXVBXOAW-rLOyPb2Rz91P1005D7jN8jE.jpeg?width=640&crop=smart&auto=webp&s=d3bccb60627b6db95d37ada09e87dd10225c58bb",
      "imageCredit": "Image via original publisher"
    },
    {
      "id": "meme_365c4e80d33c",
      "section": "meme",
      "sectionLabel": "Not-So-Serious",
      "type": "MEME",
      "category": "WEIRD",
      "title": "Orban declares Ukraine 'enemy' of Hungary",
      "dek": "submitted by /u/TailungFu [link] [comments]",
      "body": "submitted by /u/TailungFu [link] [comments]",
      "author": "IriLine Desk",
      "publishedAt": "2026-02-07T18:59:27+00:00",
      "sourceUrl": "https://www.reddit.com/r/nottheonion/comments/1qym6s4/orban_declares_ukraine_enemy_of_hungary/",
      "image": "https://external-preview.redd.it/IfjWF67freP7geQOK6lWn_VTGdIl1oLubaFiTTjOEU4.jpeg?width=640&crop=smart&auto=webp&s=eb0ad416a3e4e679b58773f2c48165f21c310b0c",
      "imageCredit": "Image via original publisher"
    },
    {
      "id": "sports_c781eb7f9436",
      "section": "sports",
      "sectionLabel": "Sports",
      "type": "REAL",
      "category": "SPORTS",
      "title": "Former MLB speedster Terrance Gore dies at 34",
      "dek": "Terrance Gore, a dynamic baserunner whose speed impacted postseason games for the better part of a decade, has died at age 34.",
      "body": "Terrance Gore, a dynamic baserunner whose speed impacted postseason games for the better part of a decade, has died at age 34.",
      "author": "IriLine Desk",
      "publishedAt": "2026-02-07T18:23:16+00:00",
      "sourceUrl": "https://www.espn.com/mlb/story/_/id/47861507/former-mlb-speedster-terrance-gore-dies-age-34",
      "image": "https://source.unsplash.com/1600x900/?news&sig=sports_c781eb7f9436",
      "imageCredit": "Photo via Unsplash (free to use)"
    },
    {
      "id": "meme_0bd20c4757c6",
      "section": "meme",
      "sectionLabel": "Not-So-Serious",
      "type": "MEME",
      "category": "WEIRD",
      "title": "GMC Made a Motorhome That Pumped Sewage Through Its Exhaust on Purpose",
      "dek": "submitted by /u/EstablishmentSoft350 [link] [comments]",
      "body": "submitted by /u/EstablishmentSoft350 [link] [comments]",
      "author": "IriLine Desk",
      "publishedAt": "2026-02-07T18:02:14+00:00",
      "sourceUrl": "https://www.reddit.com/r/nottheonion/comments/1qyko8v/gmc_made_a_motorhome_that_pumped_sewage_through/",
      "image": "https://external-preview.redd.it/Tcl3XebeyYMABkWuyWcfc0OwasHWq03wxjsX1tKP1Yw.jpeg?width=640&crop=smart&auto=webp&s=7d6c61fcc31c98edaaed49b1e1d00fe343cedb4b",
      "imageCredit": "Image via original publisher"
    },
    {
      "id": "latest_f9c52f222943",
      "section": "latest",
      "sectionLabel": "Latest",
      "type": "REAL",
      "category": "WORLD",
      "title": "Alleged mastermind among four arrested after Pakistan mosque blast",
      "dek": "The four are suspected of facilitating a suicide bombing that killed more than 30 people, Pakistan's interior minister said.",
      "body": "The four are suspected of facilitating a suicide bombing that killed more than 30 people, Pakistan's interior minister said.",
      "author": "IriLine Desk",
      "publishedAt": "2026-02-07T17:58:37+00:00",
      "sourceUrl": "https://www.bbc.com/news/articles/cd6w69pj14xo?at_medium=RSS&at_campaign=rss",
      "image": "https://ichef.bbci.co.uk/ace/standard/240/cpsprodpb/46c7/live/e2669cf0-044b-11f1-b5e2-dd58fc65f0f6.jpg",
      "imageCredit": "Image via original publisher"
    },
    {
      "id": "meme_b0a5928c4f69",
      "section": "meme",
      "sectionLabel": "Not-So-Serious",
      "type": "MEME",
      "category": "WEIRD",
      "title": "A Biopharmaceutical Company Is Actually Testing a Weight Loss Drug for Cats",
      "dek": "submitted by /u/StemCellPirate [link] [comments]",
      "body": "submitted by /u/StemCellPirate [link] [comments]",
      "author": "IriLine Desk",
      "publishedAt": "2026-02-07T17:34:33+00:00",
      "sourceUrl": "https://www.reddit.com/r/nottheonion/comments/1qyjxjx/a_biopharmaceutical_company_is_actually_testing_a/",
      "image": "https://external-preview.redd.it/-d70-0d7k2u2cr45YkRAgt5YlhL9d5CAtwUUD2fRV9g.jpeg?width=640&crop=smart&auto=webp&s=4975204ff5e1eb2828c3df7543017b04a6c69cf0",
      "imageCredit": "Image via original publisher"
    },
    {
      "id": "latest_f7e157a30d0b",
      "section": "latest",
      "sectionLabel": "Latest",
      "type": "REAL",
      "category": "WORLD",
      "title": "France investigates ex-minister Jack Lang over Epstein links",
      "dek": "The socialist grandee and his daughter are being investigated for suspected \"laundering of tax-fraud proceeds\".",
      "body": "The socialist grandee and his daughter are being investigated for suspected \"laundering of tax-fraud proceeds\".",
      "author": "IriLine Desk",
      "publishedAt": "2026-02-07T17:25:01+00:00",
      "sourceUrl": "https://www.bbc.com/news/articles/crkrk567d7zo?at_medium=RSS&at_campaign=rss",
      "image": "https://ichef.bbci.co.uk/ace/standard/240/cpsprodpb/cead/live/a44d7860-043e-11f1-ac32-dfe0213e34da.png",
      "imageCredit": "Image via original publisher"
    },
    {
      "id": "sports_6c8dbff01885",
      "section": "sports",
      "sectionLabel": "Sports",
      "type": "REAL",
      "category": "SPORTS",
      "title": "Japan grabs gold, silver medals in men's big air",
      "dek": "Kira Kimura and Ryoma Kimata led a Japanese gold and silver medal grab in men's big air on Saturday, underlining the growing dominance of their country in snowb",
      "body": "Kira Kimura and Ryoma Kimata led a Japanese gold and silver medal grab in men's big air on Saturday, underlining the growing dominance of their country in snowboarding at the Winter Olympics.",
      "author": "IriLine Desk",
      "publishedAt": "2026-02-07T17:22:59+00:00",
      "sourceUrl": "https://www.espn.com/olympics/story/_/id/47859864/japan-extends-men-snowboarding-big-air-dominance-olympics",
      "image": "https://source.unsplash.com/1600x900/?news&sig=sports_6c8dbff01885",
      "imageCredit": "Photo via Unsplash (free to use)"
    }
  ]
}