{
  "generatedAt": "2026-02-19T11:55:17+00:00",
  "items": [
    {
      "id": "meme_1382e62b83e7",
      "section": "meme",
      "sectionLabel": "Not-So-Serious",
      "type": "MEME",
      "category": "WEIRD",
      "title": "St. Petersburg State University offers students €550 signing bonus for enlisting in military",
      "dek": "submitted by /u/duckanroll [link] [comments]",
      "body": "submitted by /u/duckanroll [link] [comments]",
      "author": "IriLine Desk",
      "publishedAt": "2026-02-19T09:47:52+00:00",
      "sourceUrl": "https://www.reddit.com/r/nottheonion/comments/1r8v32g/st_petersburg_state_university_offers_students/",
      "image": "https://external-preview.redd.it/UtMYBI62xVu-ONJTavWbaFfcHIY8_9jBPTxadTwMc2M.jpeg?width=640&crop=smart&auto=webp&s=0f521cf6440c488fe4abe379fd29ec2550bb1026",
      "imageCredit": "Image via original publisher"
    },
    {
      "id": "latest_017f35bf7ced",
      "section": "latest",
      "sectionLabel": "Latest",
      "type": "REAL",
      "category": "WORLD",
      "title": "South Korea's ex-president jailed for life over martial law attempt",
      "dek": "Yoon Suk Yeol's December 2024 martial law bid fundamentally damaged South Korea's democracy, a judge told the court.",
      "body": "Yoon Suk Yeol's December 2024 martial law bid fundamentally damaged South Korea's democracy, a judge told the court.",
      "author": "IriLine Desk",
      "publishedAt": "2026-02-19T09:46:55+00:00",
      "sourceUrl": "https://www.bbc.com/news/articles/cx28y8xd1vjo?at_medium=RSS&at_campaign=rss",
      "image": "https://ichef.bbci.co.uk/ace/standard/240/cpsprodpb/ab04/live/3ed0c190-0d71-11f1-b1f2-a50c2c5773ab.jpg",
      "imageCredit": "Image via original publisher"
    },
    {
      "id": "meme_c97363efabc4",
      "section": "meme",
      "sectionLabel": "Not-So-Serious",
      "type": "MEME",
      "category": "WEIRD",
      "title": "Zuckerberg defends Meta in landmark social media addiction trial",
      "dek": "submitted by /u/Sea_Building_104 [link] [comments]",
      "body": "submitted by /u/Sea_Building_104 [link] [comments]",
      "author": "IriLine Desk",
      "publishedAt": "2026-02-19T06:34:35+00:00",
      "sourceUrl": "https://www.reddit.com/r/nottheonion/comments/1r8ryab/zuckerberg_defends_meta_in_landmark_social_media/",
      "image": "https://external-preview.redd.it/y55nTPbweyeAW0GffLibhwk8Ic757kc-2RW3bwK9EOE.png?width=640&crop=smart&auto=webp&s=c94045986059c97c9ccda8edcb83392f17463c78",
      "imageCredit": "Image via original publisher"
    }
  ]
}