{
  "generatedAt": "2026-07-17T01:04:29+00:00",
  "items": [
    {
      "id": "meme_0ff2885086b0",
      "section": "meme",
      "sectionLabel": "Not-So-Serious",
      "type": "MEME",
      "category": "WEIRD",
      "title": "AP Exclusive: ICE officer in Maine shooting has history of violent behavior, family and records say (Associated Press)",
      "dek": "submitted by /u/EmptyCaterpillar6969 [link] [comments]",
      "body": "submitted by /u/EmptyCaterpillar6969 [link] [comments]",
      "author": "IriLine Desk",
      "publishedAt": "2026-07-17T00:23:39+00:00",
      "sourceUrl": "https://www.reddit.com/r/nottheonion/comments/1uyk8yd/ap_exclusive_ice_officer_in_maine_shooting_has/",
      "image": "https://source.unsplash.com/1600x900/?news&sig=meme_0ff2885086b0",
      "imageCredit": "Photo via Unsplash (free to use)"
    },
    {
      "id": "meme_91810c1a5fc0",
      "section": "meme",
      "sectionLabel": "Not-So-Serious",
      "type": "MEME",
      "category": "WEIRD",
      "title": "A Kalshi ad from a 250 Anniversary campaign depicting bets on whether baseball would end segregation or not has been pulled after severe backlash",
      "dek": "submitted by /u/Tsunamix0147 [link] [comments]",
      "body": "submitted by /u/Tsunamix0147 [link] [comments]",
      "author": "IriLine Desk",
      "publishedAt": "2026-07-17T00:19:11+00:00",
      "sourceUrl": "https://www.reddit.com/r/nottheonion/comments/1uyk5gi/a_kalshi_ad_from_a_250_anniversary_campaign/",
      "image": "https://external-preview.redd.it/6cyih_YRPM1ACOc-Z5_9wJVLCLplin3Rmk_VHpBSB14.jpeg?width=320&crop=smart&auto=webp&s=47a26a8575ee0d0b1cd2c66cbb556db0e4e15a7d",
      "imageCredit": "Image via original publisher"
    },
    {
      "id": "meme_2559e2e76d5b",
      "section": "meme",
      "sectionLabel": "Not-So-Serious",
      "type": "MEME",
      "category": "WEIRD",
      "title": "Iran warned Vance that Kushner, Witkoff used peace talks as cover for insider trading: Report",
      "dek": "submitted by /u/No_Mercy_4_Potatoes [link] [comments]",
      "body": "submitted by /u/No_Mercy_4_Potatoes [link] [comments]",
      "author": "IriLine Desk",
      "publishedAt": "2026-07-16T23:53:35+00:00",
      "sourceUrl": "https://www.reddit.com/r/nottheonion/comments/1uyjjxf/iran_warned_vance_that_kushner_witkoff_used_peace/",
      "image": "https://external-preview.redd.it/Uv5FGCZGgQNNJp55ivb_vtQ9HvxhcvSQnRaEDgpa0M0.jpeg?width=640&crop=smart&auto=webp&s=781b450dcbd53a9308ba929bb4003196f0936224",
      "imageCredit": "Image via original publisher"
    }
  ]
}