{
  "generatedAt": "2026-06-18T14:12:25+00:00",
  "items": [
    {
      "id": "meme_0ce01a444176",
      "section": "meme",
      "sectionLabel": "Not-So-Serious",
      "type": "MEME",
      "category": "WEIRD",
      "title": "Mick Wallace says there is ‘more democracy in Iran than in most other countries’ after accepting award in Tehran",
      "dek": "submitted by /u/Firecracker048 [link] [comments]",
      "body": "submitted by /u/Firecracker048 [link] [comments]",
      "author": "IriLine Desk",
      "publishedAt": "2026-06-18T14:03:36+00:00",
      "sourceUrl": "https://www.reddit.com/r/nottheonion/comments/1u976a6/mick_wallace_says_there_is_more_democracy_in_iran/",
      "image": "https://source.unsplash.com/1600x900/?news&sig=meme_0ce01a444176",
      "imageCredit": "Photo via Unsplash (free to use)"
    },
    {
      "id": "latest_be11e9e967e5",
      "section": "latest",
      "sectionLabel": "Latest",
      "type": "REAL",
      "category": "WORLD",
      "title": "Apple to raise prices as AI boom pushes up chip costs",
      "dek": "The firm's outgoing boss Tim Cook did not say when prices would rise or which products would be affected.",
      "body": "The firm's outgoing boss Tim Cook did not say when prices would rise or which products would be affected.",
      "author": "IriLine Desk",
      "publishedAt": "2026-06-18T14:03:27+00:00",
      "sourceUrl": "https://www.bbc.com/news/articles/c3wyxvqdx1zo?at_medium=RSS&at_campaign=rss",
      "image": "https://ichef.bbci.co.uk/ace/standard/240/cpsprodpb/09cb/live/82d01bd0-6aa9-11f1-9a45-c56b5234f7dc.jpg",
      "imageCredit": "Image via original publisher"
    },
    {
      "id": "latest_a7e6a5bd9d23",
      "section": "latest",
      "sectionLabel": "Latest",
      "type": "REAL",
      "category": "WORLD",
      "title": "First Russian shadow fleet tanker enters Channel since Smyrtos boarding",
      "dek": "Forwarder, a Russian-flagged ship which left port in Primorsk last week, entered the Channel on Wednesday evening.",
      "body": "Forwarder, a Russian-flagged ship which left port in Primorsk last week, entered the Channel on Wednesday evening.",
      "author": "IriLine Desk",
      "publishedAt": "2026-06-18T14:02:52+00:00",
      "sourceUrl": "https://www.bbc.com/news/articles/cgk6d12lz6jo?at_medium=RSS&at_campaign=rss",
      "image": "https://ichef.bbci.co.uk/ace/standard/240/cpsprodpb/4f9c/live/d741c4e0-6b0b-11f1-b1db-af71d47507d6.jpg",
      "imageCredit": "Image via original publisher"
    }
  ]
}