{
  "generatedAt": "2026-04-02T11:11:32+00:00",
  "items": [
    {
      "id": "latest_bfcf7e1f6b28",
      "section": "latest",
      "sectionLabel": "Latest",
      "type": "REAL",
      "category": "WORLD",
      "title": "Over 1,800 killed since junta seized power in Burkina Faso, rights group says",
      "dek": "Human Rights Watch says Capt Traoré, other military leaders and jihadists \"may be liable\" for the killings.",
      "body": "Human Rights Watch says Capt Traoré, other military leaders and jihadists \"may be liable\" for the killings.",
      "author": "IriLine Desk",
      "publishedAt": "2026-04-02T11:11:03+00:00",
      "sourceUrl": "https://www.bbc.com/news/articles/ckgr639007zo?at_medium=RSS&at_campaign=rss",
      "image": "https://ichef.bbci.co.uk/ace/standard/240/cpsprodpb/6df4/live/172c2bc0-2e78-11f1-8dc4-7bd9501845f2.jpg",
      "imageCredit": "Image via original publisher"
    },
    {
      "id": "meme_f898ce2f9538",
      "section": "meme",
      "sectionLabel": "Not-So-Serious",
      "type": "MEME",
      "category": "WEIRD",
      "title": "Satire is a vital tool for challenging power, and it's being undermined",
      "dek": "submitted by /u/whoamisri [link] [comments]",
      "body": "submitted by /u/whoamisri [link] [comments]",
      "author": "IriLine Desk",
      "publishedAt": "2026-04-02T11:01:58+00:00",
      "sourceUrl": "https://www.reddit.com/r/nottheonion/comments/1sae90c/satire_is_a_vital_tool_for_challenging_power_and/",
      "image": "https://external-preview.redd.it/6NLeggXzY6YeZQM8Eu2kzlfjtjssIxSPXwE6KyDthEc.jpeg?width=640&crop=smart&auto=webp&s=28385f2dca4f44f2e3b991c372345be87cb05513",
      "imageCredit": "Image via original publisher"
    },
    {
      "id": "latest_9ba9e0cdbd0b",
      "section": "latest",
      "sectionLabel": "Latest",
      "type": "REAL",
      "category": "WORLD",
      "title": "Brazil grants joint custody over pets in new law for separated couples",
      "dek": "Lawmakers in the Brazilian Congress on Tuesday viewed the law change as a reflection on the importance people place on their pets.",
      "body": "Lawmakers in the Brazilian Congress on Tuesday viewed the law change as a reflection on the importance people place on their pets.",
      "author": "IriLine Desk",
      "publishedAt": "2026-04-02T09:38:08+00:00",
      "sourceUrl": "https://www.bbc.com/news/articles/ce8jzn180x2o?at_medium=RSS&at_campaign=rss",
      "image": "https://ichef.bbci.co.uk/ace/standard/240/cpsprodpb/e981/live/14bb9760-2e6c-11f1-9408-ab8675603e32.jpg",
      "imageCredit": "Image via original publisher"
    }
  ]
}